README.md
setup.py
KSTLogger/__init__.py
funky_chicken_logger.egg-info/PKG-INFO
funky_chicken_logger.egg-info/SOURCES.txt
funky_chicken_logger.egg-info/dependency_links.txt
funky_chicken_logger.egg-info/top_level.txt