Metadata-Version: 2.1
Name: funky-chicken-logger
Version: 0.2.0
Summary: Is it a great logger? No. Do I plan to make it better? Also, no.
